important/__init__.py
important/__main__.py
important/check.py
important/parse.py
important-0.1.4.dist-info/DESCRIPTION.rst
important-0.1.4.dist-info/LICENSE.txt
important-0.1.4.dist-info/METADATA
important-0.1.4.dist-info/RECORD
important-0.1.4.dist-info/WHEEL
important-0.1.4.dist-info/entry_points.txt
important-0.1.4.dist-info/metadata.json
important-0.1.4.dist-info/top_level.txt
