Metadata-Version: 2.0
Name: important
Version: 0.1.4
Summary: Utility to find unused packages in requirements  and to constrain package usage
Home-page: https://github.com/cfournie/important
Author: Chris Fournier
Author-email: chris.m.fournier@gmail.com
License: MIT
Download-URL: https://github.com/cfournie/important/tarball/0.1.4
Keywords: import,requirement,unused
Platform: UNKNOWN
Classifier: Development Status :: 4 - Beta
Classifier: Intended Audience :: Developers
Classifier: Topic :: Software Development :: Build Tools
Classifier: Topic :: Software Development :: Testing
Classifier: License :: OSI Approved :: MIT License
Classifier: Programming Language :: Python :: 2
Classifier: Programming Language :: Python :: 2.7
Classifier: Programming Language :: Python :: 3
Classifier: Programming Language :: Python :: 3.3
Classifier: Programming Language :: Python :: 3.4
Classifier: Programming Language :: Python :: 3.5
Classifier: Programming Language :: Python :: 3.6
Requires-Dist: click (>=5)
Requires-Dist: pip (>=8)
Requires-Dist: setuptools (>=0.9)
